setup.py
Proximate.egg-info/PKG-INFO
Proximate.egg-info/SOURCES.txt
Proximate.egg-info/dependency_links.txt
Proximate.egg-info/entry_points.txt
Proximate.egg-info/not-zip-safe
Proximate.egg-info/requires.txt
Proximate.egg-info/top_level.txt
proximate/__init__.py
proximate/proxy.py